<?xml version="1.0" encoding="utf-8"?>
<Dependencies>
  <Dependency>
    <ExtensionId>Lucene</ExtensionId>
    <LoaderName>PrecompiledExtensionLoader</LoaderName>
    <VirtualPath>~/Modules/Lucene/bin/Lucene.dll</VirtualPath>
    <Hash>922aec7180247eba</Hash>
  </Dependency>
  <Dependency>
    <ExtensionId>Markdown</ExtensionId>
    <LoaderName>PrecompiledExtensionLoader</LoaderName>
    <VirtualPath>~/Modules/Markdown/bin/Markdown.dll</VirtualPath>
    <Hash>923ea48542d88aee</Hash>
  </Dependency>
  <Dependency>
    <ExtensionId>Orchard.Alias</ExtensionId>
    <LoaderName>PrecompiledExtensionLoader</LoaderName>
    <VirtualPath>~/Modules/Orchard.Alias/bin/Orchard.Alias.dll</VirtualPath>
    <Hash>48fac14c7f23718f</Hash>
  </Dependency>
  <Dependency>
    <ExtensionId>Orchard.AntiSpam</ExtensionId>
    <LoaderName>PrecompiledExtensionLoader</LoaderName>
    <VirtualPath>~/Modules/Orchard.AntiSpam/bin/Orchard.AntiSpam.dll</VirtualPath>
    <Hash>9258aafc515b864d</Hash>
  </Dependency>
  <Dependency>
    <ExtensionId>Orchard.ArchiveLater</ExtensionId>
    <LoaderName>PrecompiledExtensionLoader</LoaderName>
    <VirtualPath>~/Modules/Orchard.ArchiveLater/bin/Orchard.ArchiveLater.dll</VirtualPath>
    <Hash>4912416408a44e9b</Hash>
  </Dependency>
  <Dependency>
    <ExtensionId>Orchard.Autoroute</ExtensionId>
    <LoaderName>PrecompiledExtensionLoader</LoaderName>
    <VirtualPath>~/Modules/Orchard.Autoroute/bin/Orchard.Autoroute.dll</VirtualPath>
    <Hash>dbac04a17f947175</Hash>
  </Dependency>
  <Dependency>
    <ExtensionId>Orchard.Azure</ExtensionId>
    <LoaderName>PrecompiledExtensionLoader</LoaderName>
    <VirtualPath>~/Modules/Orchard.Azure/bin/Orchard.Azure.dll</VirtualPath>
    <Hash>be6d38a5fda7d0a2</Hash>
  </Dependency>
  <Dependency>
    <ExtensionId>Orchard.Azure.MediaServices</ExtensionId>
    <LoaderName>PrecompiledExtensionLoader</LoaderName>
    <VirtualPath>~/Modules/Orchard.Azure.MediaServices/bin/Orchard.Azure.MediaServices.dll</VirtualPath>
    <Hash>741fd11d9d4acdf7</Hash>
  </Dependency>
  <Dependency>
    <ExtensionId>Orchard.Blogs</ExtensionId>
    <LoaderName>PrecompiledExtensionLoader</LoaderName>
    <VirtualPath>~/Modules/Orchard.Blogs/bin/Orchard.Blogs.dll</VirtualPath>
    <Hash>6e65e7ff2e18a9fe</Hash>
  </Dependency>
  <Dependency>
    <ExtensionId>Orchard.Caching</ExtensionId>
    <LoaderName>PrecompiledExtensionLoader</LoaderName>
    <VirtualPath>~/Modules/Orchard.Caching/bin/Orchard.Caching.dll</VirtualPath>
    <Hash>4900d952a2d3d92b</Hash>
  </Dependency>
  <Dependency>
    <ExtensionId>Orchard.CodeGeneration</ExtensionId>
    <LoaderName>PrecompiledExtensionLoader</LoaderName>
    <VirtualPath>~/Modules/Orchard.CodeGeneration/bin/Orchard.CodeGeneration.dll</VirtualPath>
    <Hash>4918a96a6d30135a</Hash>
  </Dependency>
  <Dependency>
    <ExtensionId>Orchard.Comments</ExtensionId>
    <LoaderName>PrecompiledExtensionLoader</LoaderName>
    <VirtualPath>~/Modules/Orchard.Comments/bin/Orchard.Comments.dll</VirtualPath>
    <Hash>2506fe4e598b5d38</Hash>
  </Dependency>
  <Dependency>
    <ExtensionId>Orchard.ContentPermissions</ExtensionId>
    <LoaderName>PrecompiledExtensionLoader</LoaderName>
    <VirtualPath>~/Modules/Orchard.ContentPermissions/bin/Orchard.ContentPermissions.dll</VirtualPath>
    <Hash>6e796012a558cebd</Hash>
  </Dependency>
  <Dependency>
    <ExtensionId>Orchard.ContentPicker</ExtensionId>
    <LoaderName>PrecompiledExtensionLoader</LoaderName>
    <VirtualPath>~/Modules/Orchard.ContentPicker/bin/Orchard.ContentPicker.dll</VirtualPath>
    <Hash>49163967fec3362b</Hash>
  </Dependency>
  <Dependency>
    <ExtensionId>Orchard.ContentTypes</ExtensionId>
    <LoaderName>PrecompiledExtensionLoader</LoaderName>
    <VirtualPath>~/Modules/Orchard.ContentTypes/bin/Orchard.ContentTypes.dll</VirtualPath>
    <Hash>9266d30a79c55fed</Hash>
  </Dependency>
  <Dependency>
    <ExtensionId>Orchard.CustomForms</ExtensionId>
    <LoaderName>PrecompiledExtensionLoader</LoaderName>
    <VirtualPath>~/Modules/Orchard.CustomForms/bin/Orchard.CustomForms.dll</VirtualPath>
    <Hash>2511de5940c958ab</Hash>
  </Dependency>
  <Dependency>
    <ExtensionId>Orchard.DesignerTools</ExtensionId>
    <LoaderName>PrecompiledExtensionLoader</LoaderName>
    <VirtualPath>~/Modules/Orchard.DesignerTools/bin/Orchard.DesignerTools.dll</VirtualPath>
    <Hash>251d166479f7bd1b</Hash>
  </Dependency>
  <Dependency>
    <ExtensionId>Orchard.Email</ExtensionId>
    <LoaderName>PrecompiledExtensionLoader</LoaderName>
    <VirtualPath>~/Modules/Orchard.Email/bin/Orchard.Email.dll</VirtualPath>
    <Hash>24fc0e4367a2a603</Hash>
  </Dependency>
  <Dependency>
    <ExtensionId>Orchard.Fields</ExtensionId>
    <LoaderName>PrecompiledExtensionLoader</LoaderName>
    <VirtualPath>~/Modules/Orchard.Fields/bin/Orchard.Fields.dll</VirtualPath>
    <Hash>48fe294fef8eeb34</Hash>
  </Dependency>
  <Dependency>
    <ExtensionId>Orchard.Forms</ExtensionId>
    <LoaderName>PrecompiledExtensionLoader</LoaderName>
    <VirtualPath>~/Modules/Orchard.Forms/bin/Orchard.Forms.dll</VirtualPath>
    <Hash>48fba94d66f18d40</Hash>
  </Dependency>
  <Dependency>
    <ExtensionId>Orchard.ImageEditor</ExtensionId>
    <LoaderName>PrecompiledExtensionLoader</LoaderName>
    <VirtualPath>~/Modules/Orchard.ImageEditor/bin/Orchard.ImageEditor.dll</VirtualPath>
    <Hash>dbc86cbdf7e17fbd</Hash>
  </Dependency>
  <Dependency>
    <ExtensionId>Orchard.ImportExport</ExtensionId>
    <LoaderName>PrecompiledExtensionLoader</LoaderName>
    <VirtualPath>~/Modules/Orchard.ImportExport/bin/Orchard.ImportExport.dll</VirtualPath>
    <Hash>491459661adb100f</Hash>
  </Dependency>
  <Dependency>
    <ExtensionId>Orchard.Indexing</ExtensionId>
    <LoaderName>PrecompiledExtensionLoader</LoaderName>
    <VirtualPath>~/Modules/Orchard.Indexing/bin/Orchard.Indexing.dll</VirtualPath>
    <Hash>49052156e343ac27</Hash>
  </Dependency>
  <Dependency>
    <ExtensionId>Orchard.JobsQueue</ExtensionId>
    <LoaderName>PrecompiledExtensionLoader</LoaderName>
    <VirtualPath>~/Modules/Orchard.JobsQueue/bin/Orchard.JobsQueue.dll</VirtualPath>
    <Hash>6e6700004742e4c5</Hash>
  </Dependency>
  <Dependency>
    <ExtensionId>Orchard.jQuery</ExtensionId>
    <LoaderName>PrecompiledExtensionLoader</LoaderName>
    <VirtualPath>~/Modules/Orchard.jQuery/bin/Orchard.jQuery.dll</VirtualPath>
    <Hash>48ff715134b3a0b6</Hash>
  </Dependency>
  <Dependency>
    <ExtensionId>Orchard.Lists</ExtensionId>
    <LoaderName>PrecompiledExtensionLoader</LoaderName>
    <VirtualPath>~/Modules/Orchard.Lists/bin/Orchard.Lists.dll</VirtualPath>
    <Hash>48fbe94dade92a85</Hash>
  </Dependency>
  <Dependency>
    <ExtensionId>Orchard.Localization</ExtensionId>
    <LoaderName>PrecompiledExtensionLoader</LoaderName>
    <VirtualPath>~/Modules/Orchard.Localization/bin/Orchard.Localization.dll</VirtualPath>
    <Hash>4912b96480ce2a07</Hash>
  </Dependency>
  <Dependency>
    <ExtensionId>Orchard.Media</ExtensionId>
    <LoaderName>PrecompiledExtensionLoader</LoaderName>
    <VirtualPath>~/Modules/Orchard.Media/bin/Orchard.Media.dll</VirtualPath>
    <Hash>923ca4833dcff8c0</Hash>
  </Dependency>
  <Dependency>
    <ExtensionId>Orchard.MediaLibrary</ExtensionId>
    <LoaderName>PrecompiledExtensionLoader</LoaderName>
    <VirtualPath>~/Modules/Orchard.MediaLibrary/bin/Orchard.MediaLibrary.dll</VirtualPath>
    <Hash>92656b090cecc763</Hash>
  </Dependency>
  <Dependency>
    <ExtensionId>Orchard.MediaPicker</ExtensionId>
    <LoaderName>PrecompiledExtensionLoader</LoaderName>
    <VirtualPath>~/Modules/Orchard.MediaPicker/bin/Orchard.MediaPicker.dll</VirtualPath>
    <Hash>db9f4637c5fd3031</Hash>
  </Dependency>
  <Dependency>
    <ExtensionId>Orchard.MediaProcessing</ExtensionId>
    <LoaderName>PrecompiledExtensionLoader</LoaderName>
    <VirtualPath>~/Modules/Orchard.MediaProcessing/bin/Orchard.MediaProcessing.dll</VirtualPath>
    <Hash>250d67f7c2456ab3</Hash>
  </Dependency>
  <Dependency>
    <ExtensionId>Orchard.Migrations</ExtensionId>
    <LoaderName>PrecompiledExtensionLoader</LoaderName>
    <VirtualPath>~/Modules/Orchard.Migrations/bin/Orchard.Migrations.dll</VirtualPath>
    <Hash>490c595e1f7b441a</Hash>
  </Dependency>
  <Dependency>
    <ExtensionId>Orchard.Modules</ExtensionId>
    <LoaderName>PrecompiledExtensionLoader</LoaderName>
    <VirtualPath>~/Modules/Orchard.Modules/bin/Orchard.Modules.dll</VirtualPath>
    <Hash>49023953f748ddf4</Hash>
  </Dependency>
  <Dependency>
    <ExtensionId>Orchard.MultiTenancy</ExtensionId>
    <LoaderName>PrecompiledExtensionLoader</LoaderName>
    <VirtualPath>~/Modules/Orchard.MultiTenancy/bin/Orchard.MultiTenancy.dll</VirtualPath>
    <Hash>491359651f33b099</Hash>
  </Dependency>
  <Dependency>
    <ExtensionId>Orchard.OutputCache</ExtensionId>
    <LoaderName>PrecompiledExtensionLoader</LoaderName>
    <VirtualPath>~/Modules/Orchard.OutputCache/bin/Orchard.OutputCache.dll</VirtualPath>
    <Hash>490f99615e7c0e1a</Hash>
  </Dependency>
  <Dependency>
    <ExtensionId>Orchard.Packaging</ExtensionId>
    <LoaderName>PrecompiledExtensionLoader</LoaderName>
    <VirtualPath>~/Modules/Orchard.Packaging/bin/Orchard.Packaging.dll</VirtualPath>
    <Hash>925e1301af665b1c</Hash>
  </Dependency>
  <Dependency>
    <ExtensionId>Orchard.Pages</ExtensionId>
    <LoaderName>PrecompiledExtensionLoader</LoaderName>
    <VirtualPath>~/Modules/Orchard.Pages/bin/Orchard.Pages.dll</VirtualPath>
    <Hash>92656b09150076bb</Hash>
  </Dependency>
  <Dependency>
    <ExtensionId>Orchard.Projections</ExtensionId>
    <LoaderName>PrecompiledExtensionLoader</LoaderName>
    <VirtualPath>~/Modules/Orchard.Projections/bin/Orchard.Projections.dll</VirtualPath>
    <Hash>dbb32ca8ab6e7a7f</Hash>
  </Dependency>
  <Dependency>
    <ExtensionId>Orchard.PublishLater</ExtensionId>
    <LoaderName>PrecompiledExtensionLoader</LoaderName>
    <VirtualPath>~/Modules/Orchard.PublishLater/bin/Orchard.PublishLater.dll</VirtualPath>
    <Hash>4912e964aec08486</Hash>
  </Dependency>
  <Dependency>
    <ExtensionId>Orchard.Recipes</ExtensionId>
    <LoaderName>PrecompiledExtensionLoader</LoaderName>
    <VirtualPath>~/Modules/Orchard.Recipes/bin/Orchard.Recipes.dll</VirtualPath>
    <Hash>2506fe4e55b4f297</Hash>
  </Dependency>
  <Dependency>
    <ExtensionId>Orchard.Roles</ExtensionId>
    <LoaderName>PrecompiledExtensionLoader</LoaderName>
    <VirtualPath>~/Modules/Orchard.Roles/bin/Orchard.Roles.dll</VirtualPath>
    <Hash>24fcf6445036fad9</Hash>
  </Dependency>
  <Dependency>
    <ExtensionId>Orchard.Rules</ExtensionId>
    <LoaderName>PrecompiledExtensionLoader</LoaderName>
    <VirtualPath>~/Modules/Orchard.Rules/bin/Orchard.Rules.dll</VirtualPath>
    <Hash>24fc4e43ab68cd8c</Hash>
  </Dependency>
  <Dependency>
    <ExtensionId>Orchard.Scripting</ExtensionId>
    <LoaderName>PrecompiledExtensionLoader</LoaderName>
    <VirtualPath>~/Modules/Orchard.Scripting/bin/Orchard.Scripting.dll</VirtualPath>
    <Hash>4909095ac7ec8bc9</Hash>
  </Dependency>
  <Dependency>
    <ExtensionId>Orchard.Scripting.CSharp</ExtensionId>
    <LoaderName>PrecompiledExtensionLoader</LoaderName>
    <VirtualPath>~/Modules/Orchard.Scripting.CSharp/bin/Orchard.Scripting.CSharp.dll</VirtualPath>
    <Hash>6e68b9a50221b254</Hash>
  </Dependency>
  <Dependency>
    <ExtensionId>Orchard.Scripting.Dlr</ExtensionId>
    <LoaderName>PrecompiledExtensionLoader</LoaderName>
    <VirtualPath>~/Modules/Orchard.Scripting.Dlr/bin/Orchard.Scripting.Dlr.dll</VirtualPath>
    <Hash>15503c0eeb049c7</Hash>
  </Dependency>
  <Dependency>
    <ExtensionId>Orchard.Search</ExtensionId>
    <LoaderName>PrecompiledExtensionLoader</LoaderName>
    <VirtualPath>~/Modules/Orchard.Search/bin/Orchard.Search.dll</VirtualPath>
    <Hash>dbb7ccad514cedae</Hash>
  </Dependency>
  <Dependency>
    <ExtensionId>Orchard.SecureSocketsLayer</ExtensionId>
    <LoaderName>PrecompiledExtensionLoader</LoaderName>
    <VirtualPath>~/Modules/Orchard.SecureSocketsLayer/bin/Orchard.SecureSocketsLayer.dll</VirtualPath>
    <Hash>492771793f2e02c5</Hash>
  </Dependency>
  <Dependency>
    <ExtensionId>Orchard.Setup</ExtensionId>
    <LoaderName>PrecompiledExtensionLoader</LoaderName>
    <VirtualPath>~/Modules/Orchard.Setup/bin/Orchard.Setup.dll</VirtualPath>
    <Hash>6e5737f06f5c503a</Hash>
  </Dependency>
  <Dependency>
    <ExtensionId>Orchard.Tags</ExtensionId>
    <LoaderName>PrecompiledExtensionLoader</LoaderName>
    <VirtualPath>~/Modules/Orchard.Tags/bin/Orchard.Tags.dll</VirtualPath>
    <Hash>24f82e3f8920cf5d</Hash>
  </Dependency>
  <Dependency>
    <ExtensionId>Orchard.TaskLease</ExtensionId>
    <LoaderName>PrecompiledExtensionLoader</LoaderName>
    <VirtualPath>~/Modules/Orchard.TaskLease/bin/Orchard.TaskLease.dll</VirtualPath>
    <Hash>4908595a1d3486a0</Hash>
  </Dependency>
  <Dependency>
    <ExtensionId>Orchard.Taxonomies</ExtensionId>
    <LoaderName>PrecompiledExtensionLoader</LoaderName>
    <VirtualPath>~/Modules/Orchard.Taxonomies/bin/Orchard.Taxonomies.dll</VirtualPath>
    <Hash>250cee54522310a0</Hash>
  </Dependency>
  <Dependency>
    <ExtensionId>Orchard.Templates</ExtensionId>
    <LoaderName>PrecompiledExtensionLoader</LoaderName>
    <VirtualPath>~/Modules/Orchard.Templates/bin/Orchard.Templates.dll</VirtualPath>
    <Hash>dbaf1ca4a0cb8df6</Hash>
  </Dependency>
  <Dependency>
    <ExtensionId>Orchard.Themes</ExtensionId>
    <LoaderName>PrecompiledExtensionLoader</LoaderName>
    <VirtualPath>~/Modules/Orchard.Themes/bin/Orchard.Themes.dll</VirtualPath>
    <Hash>48fea1505ecae0fa</Hash>
  </Dependency>
  <Dependency>
    <ExtensionId>Orchard.Tokens</ExtensionId>
    <LoaderName>PrecompiledExtensionLoader</LoaderName>
    <VirtualPath>~/Modules/Orchard.Tokens/bin/Orchard.Tokens.dll</VirtualPath>
    <Hash>48ff1150cf6b5f0e</Hash>
  </Dependency>
  <Dependency>
    <ExtensionId>Orchard.Users</ExtensionId>
    <LoaderName>PrecompiledExtensionLoader</LoaderName>
    <VirtualPath>~/Modules/Orchard.Users/bin/Orchard.Users.dll</VirtualPath>
    <Hash>48fc014dc12a23c8</Hash>
  </Dependency>
  <Dependency>
    <ExtensionId>Orchard.Warmup</ExtensionId>
    <LoaderName>PrecompiledExtensionLoader</LoaderName>
    <VirtualPath>~/Modules/Orchard.Warmup/bin/Orchard.Warmup.dll</VirtualPath>
    <Hash>48ff51510fdc82bc</Hash>
  </Dependency>
  <Dependency>
    <ExtensionId>Orchard.Widgets</ExtensionId>
    <LoaderName>PrecompiledExtensionLoader</LoaderName>
    <VirtualPath>~/Modules/Orchard.Widgets/bin/Orchard.Widgets.dll</VirtualPath>
    <Hash>dbb254a7d11bd1ad</Hash>
  </Dependency>
  <Dependency>
    <ExtensionId>Orchard.Workflows</ExtensionId>
    <LoaderName>PrecompiledExtensionLoader</LoaderName>
    <VirtualPath>~/Modules/Orchard.Workflows/bin/Orchard.Workflows.dll</VirtualPath>
    <Hash>dbad1ca29714c692</Hash>
  </Dependency>
  <Dependency>
    <ExtensionId>SoftIT.CRM</ExtensionId>
    <LoaderName>DynamicExtensionLoader</LoaderName>
    <VirtualPath>~/Modules/SoftIT.CRM/SoftIT.CRM.csproj</VirtualPath>
    <Hash>8f81782964c753b9</Hash>
  </Dependency>
  <Dependency>
    <ExtensionId>SysCache</ExtensionId>
    <LoaderName>PrecompiledExtensionLoader</LoaderName>
    <VirtualPath>~/Modules/SysCache/bin/SysCache.dll</VirtualPath>
    <Hash>92655cac0127683f</Hash>
  </Dependency>
  <Dependency>
    <ExtensionId>TinyMce</ExtensionId>
    <LoaderName>PrecompiledExtensionLoader</LoaderName>
    <VirtualPath>~/Modules/TinyMce/bin/TinyMce.dll</VirtualPath>
    <Hash>48e9b13b770cd75d</Hash>
  </Dependency>
  <Dependency>
    <ExtensionId>Upgrade</ExtensionId>
    <LoaderName>PrecompiledExtensionLoader</LoaderName>
    <VirtualPath>~/Modules/Upgrade/bin/Upgrade.dll</VirtualPath>
    <Hash>265359d7d4b92c83</Hash>
  </Dependency>
</Dependencies>